{
  "trackers": [],
  "cookies": [
    {
      "name": "_pk_id.1521.e155",
      "value": "27b2d881f8e063c2.1730597636.",
      "domain": ".www.ecologie.gouv.fr",
      "path": "/",
      "expires": 1764552836,
      "size": 44,
      "httpOnly": false,
      "secure": false,
      "session": false,
      "sameSite": "Lax",
      "sameParty": false,
      "sourceScheme": "Secure",
      "sourcePort": 443
    },
    {
      "name": "_pk_ses.1521.e155",
      "value": "1",
      "domain": ".www.ecologie.gouv.fr",
      "path": "/",
      "expires": 1730599435,
      "size": 18,
      "httpOnly": false,
      "secure": false,
      "session": false,
      "sameSite": "Lax",
      "sameParty": false,
      "sourceScheme": "Secure",
      "sourcePort": 443
    },
    {
      "name": "PHPSESSID",
      "value": "ilgqavaj98ehcf8ma42al3gb06",
      "domain": "www.ecologie.gouv.fr",
      "path": "/",
      "expires": -1,
      "size": 35,
      "httpOnly": false,
      "secure": false,
      "session": true,
      "sameParty": false,
      "sourceScheme": "Secure",
      "sourcePort": 443
    },
    {
      "name": "langue-site",
      "value": "fr",
      "domain": "www.ecologie.gouv.fr",
      "path": "/",
      "expires": 1733189634,
      "size": 13,
      "httpOnly": false,
      "secure": false,
      "session": false,
      "sameParty": false,
      "sourceScheme": "Secure",
      "sourcePort": 443
    },
    {
      "name": "spip_session",
      "value": "0_fe66729d7dd40f1795acfbc1d5486b99",
      "domain": "www.ecologie.gouv.fr",
      "path": "/ouipub/",
      "expires": 1730684035.147869,
      "size": 46,
      "httpOnly": true,
      "secure": false,
      "session": false,
      "sameParty": false,
      "sourceScheme": "Secure",
      "sourcePort": 443
    }
  ],
  "headers": {
    "accept-ranges": "bytes",
    "cache-control": "max-age=900",
    "cache-tags": "HIT",
    "content-encoding": "gzip",
    "content-length": "7231",
    "content-type": "text/html; charset=utf-8",
    "date": "Sun, 03 Nov 2024 01:33:54 GMT",
    "expires": "Thu, 19 Nov 1981 08:52:00 GMT",
    "last-modified": "Sun, 03 Nov 2024 01:21:58 GMT",
    "pragma": "no-cache",
    "server": "nginx",
    "set-cookie": "PHPSESSID=ilgqavaj98ehcf8ma42al3gb06; path=/\nspip_session=0_fe66729d7dd40f1795acfbc1d5486b99; expires=Mon, 04-Nov-2024 01:21:58 GMT; Max-Age=86400; path=/ouipub/; HttpOnly\nspip_admin=deleted; expires=Thu, 01-Jan-1970 00:00:01 GMT; Max-Age=0; path=/ouipub/",
    "vary": "Cookie,Accept-Encoding",
    "x-cache": "HIT",
    "x-cache-age": "715",
    "x-cache-hits": "18",
    "x-spip-cache": "86400"
  },
  "endpoints": [
    {
      "hostname": "www.ecologie.gouv.fr",
      "ip": "37.235.89.112",
      "geoip": {
        "continent": {
          "code": "EU",
          "geoname_id": 6255148,
          "names": {
            "de": "Europa",
            "en": "Europe",
            "es": "Europa",
            "fr": "Europe",
            "ja": "ヨーロッパ",
            "pt-BR": "Europa",
            "ru": "Европа",
            "zh-CN": "欧洲"
          }
        },
        "country": {
          "geoname_id": 3017382,
          "is_in_european_union": true,
          "iso_code": "FR",
          "names": {
            "de": "Frankreich",
            "en": "France",
            "es": "Francia",
            "fr": "France",
            "ja": "フランス共和国",
            "pt-BR": "França",
            "ru": "Франция",
            "zh-CN": "法国"
          }
        },
        "location": {
          "accuracy_radius": 500,
          "latitude": 48.8582,
          "longitude": 2.3387,
          "time_zone": "Europe/Paris"
        },
        "registered_country": {
          "geoname_id": 3017382,
          "is_in_european_union": true,
          "iso_code": "FR",
          "names": {
            "de": "Frankreich",
            "en": "France",
            "es": "Francia",
            "fr": "France",
            "ja": "フランス共和国",
            "pt-BR": "França",
            "ru": "Франция",
            "zh-CN": "法国"
          }
        }
      }
    }
  ]
}
